[
  {
    "hash": "0190029B84B795FF",
    "path": "",
    "gameFlags": 1
  },
  {
    "hash": "01FA4C3550F519A4",
    "path": "[assembly:/_knt/sound/wwise/exported/switches/haptics/sw_haptics_interactions_conversations.wwiseswitchgroup].entityblueprint",
    "gameFlags": 1
  },
  {
    "hash": "01220C5B337E71D2",
    "path": "",
    "gameFlags": 1
  },
  {
    "hash": "016A3836641B21AE",
    "path": "",
    "gameFlags": 1
  },
  {
    "hash": "019E630C8CB89A37",
    "path": "",
    "gameFlags": 1
  },
  {
    "hash": "01FCF9621B51827D",
    "path": "",
    "gameFlags": 1
  },
  {
    "hash": "01DCEDA88A0B95B7",
    "path": "",
    "gameFlags": 1
  },
  {
    "hash": "0152CDF83F26ABE7",
    "path": "[assembly:/_knt/sound/wwise/exported/switches/foley/switch_fol_outfit.wwiseswitchgroup].entityblueprint",
    "gameFlags": 1
  },
  {
    "hash": "0189F02480DAF37C",
    "path": "",
    "gameFlags": 1
  },
  {
    "hash": "01FC910EFA25BCDB",
    "path": "[assembly:/_knt/sound/wwise/exported/switches/foley/switch_fs_sweetener.wwiseswitchgroup].entityblueprint",
    "gameFlags": 1
  },
  {
    "hash": "01F2AF9A5293FA0E",
    "path": "[assembly:/_knt/sound/wwise/exported/switches/haptics/haptics_door_interactions.wwiseswitchgroup].entityblueprint",
    "gameFlags": 1
  },
  {
    "hash": "010A07576DFEB8F3",
    "path": "[assembly:/_knt/sound/wwise/exported/switches/firearms/switch_fa_class.wwiseswitchgroup].entityblueprint",
    "gameFlags": 1
  },
  {
    "hash": "01B7E8ED630E4707",
    "path": "",
    "gameFlags": 1
  },
  {
    "hash": "0189F19D5DD239DC",
    "path": "",
    "gameFlags": 1
  },
  {
    "hash": "013C655B6ECCA49D",
    "path": "",
    "gameFlags": 1
  },
  {
    "hash": "01CB99F02B1D1084",
    "path": "",
    "gameFlags": 1
  },
  {
    "hash": "0116A059E33D3100",
    "path": "[assembly:/_knt/sound/wwise/exported/switches/foley/switch_fol_leftright.wwiseswitchgroup].entityblueprint",
    "gameFlags": 1
  },
  {
    "hash": "015308493DCE0240",
    "path": "[assembly:/_knt/sound/wwise/exported/switches/haptics/sw_haptics_interactions_qte.wwiseswitchgroup].entityblueprint",
    "gameFlags": 1
  },
  {
    "hash": "01C14C2865857B99",
    "path": "",
    "gameFlags": 1
  },
  {
    "hash": "016E9E2A08956249",
    "path": "",
    "gameFlags": 1
  },
  {
    "hash": "019FEF394BEFB1FA",
    "path": "",
    "gameFlags": 1
  },
  {
    "hash": "0148AC53839F2EE9",
    "path": "[assembly:/_knt/sound/wwise/exported/switches/foley/switch_fol_waterdepth.wwiseswitchgroup].entityblueprint",
    "gameFlags": 1
  },
  {
    "hash": "01B7A06DB75D62E0",
    "path": "",
    "gameFlags": 1
  },
  {
    "hash": "012B80743F20436C",
    "path": "",
    "gameFlags": 1
  },
  {
    "hash": "015DA4D56B3BD12B",
    "path": "",
    "gameFlags": 1
  }
]